local_chamber/__init__.py
local_chamber/__main__.py
local_chamber/archive.py
local_chamber/chamber.py
local_chamber/cli.py
local_chamber/exception.py
local_chamber/shell.py
local_chamber/vault.py
local_chamber/version.py
local_chamber-1.10.1.dist-info/entry_points.txt
local_chamber-1.10.1.dist-info/LICENSE
local_chamber-1.10.1.dist-info/WHEEL
local_chamber-1.10.1.dist-info/METADATA
local_chamber-1.10.1.dist-info/RECORD
