Metadata-Version: 2.1
Name: local_chamber
Version: 1.10.1
Summary: Top-level package for local-chamber.
Keywords: local-chamber
Author-email: Matt Krueger <mkrueger@rstms.net>
Classifier: Intended Audience :: Developers
Classifier: Natural Language :: English
Classifier: Programming Language :: Python :: 3
Classifier: Programming Language :: Python :: 3.7
Classifier: Programming Language :: Python :: 3.8
Classifier: Programming Language :: Python :: 3.9
Classifier: Programming Language :: Python :: 3.10
Requires-Dist: click>=8.1.3
Requires-Dist: hvac>=0.11.2
Requires-Dist: pyyaml>=5.4.1
Requires-Dist: black ; extra == "dev"
Requires-Dist: bump2version ; extra == "dev"
Requires-Dist: coverage ; extra == "dev"
Requires-Dist: flake8 ; extra == "dev"
Requires-Dist: flit ; extra == "dev"
Requires-Dist: isort ; extra == "dev"
Requires-Dist: pdbpp ; extra == "dev"
Requires-Dist: pytest ; extra == "dev"
Requires-Dist: pytest-click ; extra == "dev"
Requires-Dist: pytest-datadir ; extra == "dev"
Requires-Dist: tox ; extra == "dev"
Requires-Dist: sphinx==5.0.1 ; extra == "docs"
Requires-Dist: sphinx-click==4.1.0 ; extra == "docs"
Requires-Dist: sphinx-rtd-theme==1.0.0 ; extra == "docs"
Project-URL: Home, https://github.com/rstms/local-chamber
Provides-Extra: dev
Provides-Extra: docs
